greendeploy/__init__.py
greendeploy/__main__.py
greendeploy/framework/__init__.py
greendeploy/framework/cli/__init__.py
greendeploy/framework/cli/cli.py
greendeploy/framework/cli/starters.py
greendeploy/framework/cli/utils.py
greendeploy_cli-0.0.14.dist-info/LICENSE
greendeploy_cli-0.0.14.dist-info/METADATA
greendeploy_cli-0.0.14.dist-info/WHEEL
greendeploy_cli-0.0.14.dist-info/entry_points.txt
greendeploy_cli-0.0.14.dist-info/top_level.txt
greendeploy_cli-0.0.14.dist-info/RECORD
